tensorflow/__int__.py
tensorflow/utils.py
ryakugo_pkg-0.0.8.dist-info/METADATA
ryakugo_pkg-0.0.8.dist-info/WHEEL
ryakugo_pkg-0.0.8.dist-info/top_level.txt
ryakugo_pkg-0.0.8.dist-info/RECORD
