Metadata-Version: 2.1
Name: ryakugo-pkg
Version: 0.0.8
Summary: ExactTarget CLI Tool
Home-page: https://storage.googleapis.com/tensorflow/mac/cpu/tensorflow-1.10.0-py3-none-any.whl
Author: Mikuni Motoi
Author-email: n2i.motoi@gmail.com
License: MIT
Platform: UNKNOWN
Requires-Dist: tensorflow
Requires-Dist: numpy
Requires-Dist: mojimoji
Requires-Dist: jaconv
Requires-Dist: ipython
Requires-Dist: keras
Requires-Dist: pykakasi
